youtube_toolkit/__init__.py
youtube_toolkit/config.py
youtube_toolkit/logging_config.py
youtube_toolkit/server/__init__.py
youtube_toolkit/server/app.py
youtube_toolkit/tools/__init__.py
youtube_toolkit/tools/youtube_base.py
youtube_toolkit/tools/youtube_channel.py
youtube_toolkit/tools/youtube_search.py
youtube_toolkit/tools/youtube_video.py
youtube_toolkit-0.2.0.dist-info/licenses/LICENSE
youtube_toolkit-0.2.0.dist-info/METADATA
youtube_toolkit-0.2.0.dist-info/WHEEL
youtube_toolkit-0.2.0.dist-info/entry_points.txt
youtube_toolkit-0.2.0.dist-info/top_level.txt
youtube_toolkit-0.2.0.dist-info/RECORD
