Metadata-Version: 2.4
Name: youtube_toolkit
Version: 0.2.0
Summary: MCP server for YouTube content analysis, transcript extraction, and creator style profiling with intelligent caching and rate limit protection.
Author-email: Tim Kitchens <timkitch@codingthefuture.ai>
License: MIT
Requires-Python: <3.13,>=3.11
License-File: LICENSE
Requires-Dist: mcp>=1.0.0
Requires-Dist: mcp[cli]>=1.0.0
Requires-Dist: anyio>=4.5
Requires-Dist: starlette>=0.36.0
Requires-Dist: uvicorn>=0.27.0
Requires-Dist: google-api-python-client>=2.108.0
Requires-Dist: youtube-transcript-api>=0.6.1
Requires-Dist: python-dotenv>=1.0.0
Provides-Extra: dev
Requires-Dist: pytest>=7.0.0; extra == "dev"
Requires-Dist: pytest-asyncio>=0.21.0; extra == "dev"
Dynamic: license-file
